pilk_nogil/SilkDecoder.py
pilk_nogil/SilkEncoder.py
pilk_nogil/__init__.py
pilk_nogil/_pilk.cp39-win_amd64.pyd
pilk_nogil/_pilk.pyi
pilk_nogil-0.3.2.dist-info/LICENSE
pilk_nogil-0.3.2.dist-info/METADATA
pilk_nogil-0.3.2.dist-info/WHEEL
pilk_nogil-0.3.2.dist-info/top_level.txt
pilk_nogil-0.3.2.dist-info/RECORD
