Metadata-Version: 2.1
Name: pilk-nogil
Version: 0.3.2
Summary: python silk voice library
Home-page: https://github.com/MelodyYuuka/pilk-nogil
Download-URL: https://github.com/MelodyYuuka/pilk-nogil/releases
Author: foyou + MelodyYuuka
Author-email: yimi.0822@qq.com + a876987@126.com
Maintainer: MelodyYuuka
Maintainer-email: a876987@126.com
Keywords: silk,voice,python,extension,wechat,qq,tencent,xposed,c/c++
Classifier: Development Status :: 4 - Beta
Classifier: License :: OSI Approved :: GNU General Public License v3 (GPLv3)
Classifier: Intended Audience :: End Users/Desktop
Classifier: Natural Language :: Chinese (Simplified)
Classifier: Operating System :: Microsoft :: Windows
Classifier: Operating System :: POSIX
Classifier: Programming Language :: C
Classifier: Programming Language :: Python
Classifier: Programming Language :: Python :: 3
Classifier: Programming Language :: Python :: 3.6
Classifier: Programming Language :: Python :: 3.7
Classifier: Programming Language :: Python :: 3.8
Classifier: Programming Language :: Python :: 3.9
Classifier: Programming Language :: Python :: 3.10
Classifier: Programming Language :: Python :: 3.11
Classifier: Programming Language :: Python :: 3.12
Classifier: Topic :: Multimedia :: Sound/Audio
Requires-Python: >=3.6
License-File: LICENSE
Requires-Dist: typing-extensions
